Metadata-Version: 2.1
Name: pythoth
Version: 0.3.0
Summary: data profiling monitoring platform
Home-page: https://github.com/rafaelleinio/thoth
Author: Rafael Leiniö
License: MIT
Platform: UNKNOWN
Requires-Python: >=3.9, <4
License-File: LICENSE
Requires-Dist: prophet (<2,>=1.1)
Requires-Dist: salesforce-merlion (<2,>=1.2.3)
Requires-Dist: numpy
Requires-Dist: pandas
Requires-Dist: pyspark (<3.1,>=3.0.0)
Requires-Dist: pydeequ
Requires-Dist: pydantic
Requires-Dist: loguru
Requires-Dist: yarl
Requires-Dist: Faker
Requires-Dist: sqlmodel
Requires-Dist: sqlalchemy
Requires-Dist: pg8000
Requires-Dist: streamlit
Requires-Dist: streamlit-permalink
Requires-Dist: plotly
